LICENSE
MANIFEST.in
README.md
setup.py
wxhelper/__init__.py
wxhelper/core.py
wxhelper/events.py
wxhelper/logger.py
wxhelper/model.py
wxhelper/utils.py
wxhelper.egg-info/PKG-INFO
wxhelper.egg-info/SOURCES.txt
wxhelper.egg-info/dependency_links.txt
wxhelper.egg-info/requires.txt
wxhelper.egg-info/top_level.txt
wxhelper/tools/config.ini
wxhelper/tools/faker.exe
wxhelper/tools/start-wechat.exe
wxhelper/tools/wxhelper.dll
wxhelper/tools/wxhelper.json