Metadata-Version: 2.1
Name: wxhelper
Version: 0.0.7
Summary: wechat robot framework.
Home-page: https://github.com/miloira/wxhelper
Author: Msky
Author-email: 690126048@qq.com
License: MIT
Classifier: License :: OSI Approved :: MIT License
Classifier: Programming Language :: Python
Classifier: Programming Language :: Python :: 3
Classifier: Programming Language :: Python :: 3.8
Classifier: Programming Language :: Python :: Implementation :: CPython
Classifier: Programming Language :: Python :: Implementation :: PyPy
Requires-Python: >=3.8.0
License-File: LICENSE
Requires-Dist: loguru
Requires-Dist: psutil
Requires-Dist: pyee
Requires-Dist: requests
Requires-Dist: xmltodict
